runegraft/__init__.py
runegraft/__main__.py
runegraft/builtins.py
runegraft/cli.py
runegraft/formatting.py
runegraft/parser.py
runegraft/shell.py
runegraft/types.py
runegraft-0.1.1.dist-info/METADATA
runegraft-0.1.1.dist-info/WHEEL
runegraft-0.1.1.dist-info/entry_points.txt
runegraft-0.1.1.dist-info/RECORD
