Metadata-Version: 2.4
Name: runegraft
Version: 0.1.1
Summary: Route-style decorator CLI with an interactive shell (REPL), completion, and history.
Project-URL: Homepage, https://runegraft.codesft.dev
Project-URL: Repository, https://github.com/CodeSoftGit/runegraft
Author: codesft
License: MIT
Requires-Python: >=3.11
Requires-Dist: prompt-toolkit>=3.0
Requires-Dist: rich>=13.0
